mlsdm/.Rhistory
mlsdm/__init__.py
mlsdm/mlsdm.py
mlsdm-0.1.0.dist-info/METADATA
mlsdm-0.1.0.dist-info/WHEEL
mlsdm-0.1.0.dist-info/licenses/LICENSE
mlsdm-0.1.0.dist-info/RECORD
