Metadata-Version: 2.4
Name: mlsdm
Version: 0.1.0
Summary: Machine Learning based Species Distribution Modeling Library for Python > 3.6
Author-email: Pranav Kulkarni <pskul@ucdavis.edu>, Pranav Pandit <pspandit@ucdavis.edu>
License: MIT
License-File: LICENSE
Requires-Python: >=3.6
Requires-Dist: geopandas>=0.10.0
Requires-Dist: lightgbm>=3.3.0
Requires-Dist: matplotlib>=3.5.0
Requires-Dist: numpy>=2.0.0
Requires-Dist: pandas>=1.5.0
Requires-Dist: pyimpute>=0.1.0
Requires-Dist: rasterio>=1.2.0
Requires-Dist: rioxarray>=0.9.0
Requires-Dist: scikit-learn>=1.0.0
Requires-Dist: scipy>=1.7.0
Requires-Dist: shapely>=1.8.0
Requires-Dist: xarray>=0.20.0
Requires-Dist: xgboost>=1.5.0
